niorclconn/__init__.py
niorclconn/connector.py
niorclconn-0.1.0.dist-info/LICENSE
niorclconn-0.1.0.dist-info/METADATA
niorclconn-0.1.0.dist-info/WHEEL
niorclconn-0.1.0.dist-info/RECORD
