Metadata-Version: 2.3
Name: niorclconn
Version: 0.1.0
Summary: A Python package for Oracle database connections with environment variable support
License: MIT
Keywords: oracle,database,connection,oracledb
Author: Deb Mishra
Author-email: infra@daedal.org
Requires-Python: >=3.9,<4.0
Classifier: Development Status :: 3 - Alpha
Classifier: Intended Audience :: Developers
Classifier: License :: OSI Approved :: MIT License
Classifier: Programming Language :: Python :: 3
Classifier: Programming Language :: Python :: 3.9
Classifier: Programming Language :: Python :: 3.10
Classifier: Programming Language :: Python :: 3.11
Classifier: Programming Language :: Python :: 3.12
Classifier: Programming Language :: Python :: 3.13
Requires-Dist: oracledb (>=2.0.0)
Project-URL: Homepage, https://github.com/yourusername/niorclconn
Project-URL: Repository, https://github.com/yourusername/niorclconn
